staff/__init__.py
staff/api.py
staff/client.py
staff/models.py
staff-0.2.0.dist-info/licenses/LICENSE.txt
staff-0.2.0.dist-info/METADATA
staff-0.2.0.dist-info/WHEEL
staff-0.2.0.dist-info/top_level.txt
staff-0.2.0.dist-info/RECORD
