Metadata-Version: 2.4
Name: Staff
Version: 0.2.0
Summary: Unofficial Python library to work with data on The StoryGraph.
Author-email: Terrance <pypi+staff@terrance.allofti.me>
License: BSD 3-Clause License
Project-URL: Source, https://github.com/Terrance/Staff
Keywords: storygraph,reading,books
Classifier: Development Status :: 3 - Alpha
Classifier: Intended Audience :: Developers
Classifier: License :: OSI Approved :: BSD License
Classifier: Operating System :: OS Independent
Classifier: Programming Language :: Python :: 3.8
Classifier: Topic :: Internet
Classifier: Topic :: Utilities
Requires-Python: >=3.8
License-File: LICENSE.txt
Requires-Dist: beautifulsoup4
Requires-Dist: requests
Dynamic: license-file
